tianchi/__init__.py
tianchi/globalvar.py
tianchi/inferServer.py
tianchi/log.py
tianchi/notice.py
tianchi/test.py
tianchi/test_gpu.py
tianchi-0.0.1.dist-info/METADATA
tianchi-0.0.1.dist-info/WHEEL
tianchi-0.0.1.dist-info/top_level.txt
tianchi-0.0.1.dist-info/RECORD
