Metadata-Version: 2.1
Name: tianchi
Version: 0.0.1
Summary: tianchi competition utils package
Home-page: https://github.com/gaoxiaos/AI_HUB
Author: gaoxiaos
Author-email: ai_hub@qq.com
License: MIT
Platform: UNKNOWN
Classifier: Programming Language :: Python :: 3
Classifier: License :: OSI Approved :: MIT License
Classifier: Operating System :: OS Independent
Requires-Dist: requests (>=1.0.0)
